qa/__init__.py
openqa-0.1.0.dist-info/METADATA
openqa-0.1.0.dist-info/WHEEL
openqa-0.1.0.dist-info/licenses/LICENSE
openqa-0.1.0.dist-info/RECORD
