Metadata-Version: 2.3
Name: openQA
Version: 0.1.0
Summary: Add your description here
Author-email: Lulzx <wiserishabh@gmail.com>
License-File: LICENSE
Requires-Python: >=3.8
Requires-Dist: ruff>=0.4.2
